pyalgotrading/__init__.py
pyalgotrading/constants.py
pyalgotrading/algobulls/__init__.py
pyalgotrading/algobulls/api.py
pyalgotrading/algobulls/connection.py
pyalgotrading/algobulls/exceptions.py
pyalgotrading/broker/__init__.py
pyalgotrading/broker/broker_connection_base.py
pyalgotrading/broker/broker_connection_zerodha.py
pyalgotrading/broker/utils.py
pyalgotrading/indicator/__init__.py
pyalgotrading/indicator/vwap.py
pyalgotrading/instrument/__init__.py
pyalgotrading/instrument/instrument.py
pyalgotrading/order/__init__.py
pyalgotrading/order/order_base.py
pyalgotrading/order/order_bracket_base.py
pyalgotrading/order/order_regular_base.py
pyalgotrading/strategy/__init__.py
pyalgotrading/strategy/strategy_base.py
pyalgotrading/strategy/strategy_options_base_v2.py
pyalgotrading/strategy/utils.py
pyalgotrading/strategy/validate_strategy.py
pyalgotrading/talib/__init__.py
pyalgotrading/talib/talib.py
pyalgotrading/utils/__init__.py
pyalgotrading/utils/func.py
pyalgotrading/utils/candlesticks/__init__.py
pyalgotrading/utils/candlesticks/heikinashi.py
pyalgotrading/utils/candlesticks/linebreak.py
pyalgotrading/utils/candlesticks/renko.py
pyalgotrading-2025.9.1.dist-info/LICENSE
pyalgotrading-2025.9.1.dist-info/METADATA
pyalgotrading-2025.9.1.dist-info/WHEEL
pyalgotrading-2025.9.1.dist-info/top_level.txt
pyalgotrading-2025.9.1.dist-info/RECORD
