Metadata-Version: 2.1
Name: pyalgotrading
Version: 2025.9.1
Summary: Official Python Package for Algorithmic Trading APIs powered by AlgoBulls
Home-page: https://github.com/algobulls/pyalgotrading
Author: Pushpak Dagade
Author-email: pushpak@algobulls.com
Project-URL: Source, https://github.com/algobulls/pyalgotrading
Project-URL: Documentation, https://algobulls.github.io/pyalgotrading/
Project-URL: Bug Reports, https://github.com/algobulls/pyalgotrading/issues
Project-URL: Say Thanks!, https://saythanks.io/to/guanidene%40gmail.com
Keywords: algotrading algorithmictrading trading strategies algostrategies apis
Classifier: Development Status :: 3 - Alpha
Classifier: Intended Audience :: Developers
Classifier: Intended Audience :: Financial and Insurance Industry
Classifier: Topic :: Software Development :: Libraries
Classifier: Topic :: Office/Business :: Financial
Classifier: Topic :: Software Development :: Libraries :: Python Modules
Classifier: License :: OSI Approved :: MIT License
Classifier: Programming Language :: Python :: 3
Classifier: Programming Language :: Python :: 3.6
Classifier: Programming Language :: Python :: 3.7
Classifier: Programming Language :: Python :: 3.8
Requires-Python: >=3.6
License-File: LICENSE
Requires-Dist: requests >=2.24.0
Requires-Dist: pandas >=0.25.3
